a2c_ase/__init__.py
a2c_ase/runner.py
a2c_ase/utils.py
a2c_ase/potentials/__init__.py
a2c_ase/potentials/mlj.py
a2c_ase/potentials/soft_sphere.py
a2c_ase-0.0.5.dist-info/licenses/LICENSE
a2c_ase-0.0.5.dist-info/METADATA
a2c_ase-0.0.5.dist-info/WHEEL
a2c_ase-0.0.5.dist-info/top_level.txt
a2c_ase-0.0.5.dist-info/RECORD
