Metadata-Version: 2.4
Name: a2c_ase
Version: 0.0.5
Summary: ASE friendly implementation of the a2c workflow with MLIPs
Author-email: Abhijeet Gangan <abhijeetgangan@g.ucla.edu>
License: MIT License
Requires-Python: >=3.10
License-File: LICENSE
Requires-Dist: ase
Requires-Dist: numpy
Requires-Dist: pymatgen
Requires-Dist: tqdm
Provides-Extra: dev
Requires-Dist: pre-commit; extra == "dev"
Requires-Dist: ruff; extra == "dev"
Requires-Dist: ty>=0.0.1a20; extra == "dev"
Provides-Extra: test
Requires-Dist: pytest; extra == "test"
Requires-Dist: pytest-cov; extra == "test"
Provides-Extra: docs
Requires-Dist: mkdocs-material>=9.0; extra == "docs"
Requires-Dist: mkdocstrings[python]>=0.24; extra == "docs"
Requires-Dist: mkdocs-jupyter>=0.24; extra == "docs"
Requires-Dist: jupytext>=1.16; extra == "docs"
Requires-Dist: ipykernel>=6.0; extra == "docs"
Dynamic: license-file
